ovos_media/__init__.py
ovos_media/__main__.py
ovos_media/gui.py
ovos_media/mpris.py
ovos_media/player.py
ovos_media/service.py
ovos_media/utils.py
ovos_media/version.py
ovos_media/media_backends/__init__.py
ovos_media/media_backends/audio.py
ovos_media/media_backends/base.py
ovos_media/media_backends/video.py
ovos_media/media_backends/web.py
ovos_media-0.0.1a22.dist-info/LICENSE.md
ovos_media-0.0.1a22.dist-info/METADATA
ovos_media-0.0.1a22.dist-info/WHEEL
ovos_media-0.0.1a22.dist-info/entry_points.txt
ovos_media-0.0.1a22.dist-info/top_level.txt
ovos_media-0.0.1a22.dist-info/RECORD
