Metadata-Version: 2.1
Name: ovos-media
Version: 0.0.1a22
Summary: ovos-core audio daemon client
Home-page: https://github.com/OpenVoiceOS/ovos-media
License: Apache-2.0
Platform: UNKNOWN
Classifier: Development Status :: 4 - Beta
Classifier: Programming Language :: Python :: 3
Classifier: License :: OSI Approved :: Apache Software License
Requires-Dist: ovos-utils >=0.1.0a13,~=0.0
Requires-Dist: ovos-bus-client >=0.0.9a11,~=0.0
Requires-Dist: ovos-config >=0.0.12,~=0.0
Requires-Dist: ovos-plugin-manager >=0.0.25,~=0.0
Requires-Dist: dbus-next
Provides-Extra: extras
Requires-Dist: ovos-ocp-youtube-plugin ; extra == 'extras'
Requires-Dist: ovos-ocp-m3u-plugin ; extra == 'extras'
Requires-Dist: ovos-ocp-rss-plugin ; extra == 'extras'
Requires-Dist: ovos-ocp-files-plugin ; extra == 'extras'
Requires-Dist: ovos-ocp-news-plugin ; extra == 'extras'
